cloudapp/__init__.py
cloudapp-0.0.0.dev0.dist-info/METADATA
cloudapp-0.0.0.dev0.dist-info/RECORD
cloudapp-0.0.0.dev0.dist-info/WHEEL
cloudapp-0.0.0.dev0.dist-info/entry_points.txt
cloudapp-0.0.0.dev0.dist-info/top_level.txt
